antchain/__init__.py
antchain/core.py
antchain/strategies.py
antchain/utils.py
antchain-0.0.6.dist-info/METADATA
antchain-0.0.6.dist-info/WHEEL
antchain-0.0.6.dist-info/RECORD
