Metadata-Version: 2.4
Name: antchain
Version: 0.0.6
Summary: 一个函数式编程风格的数据流式处理管道库，支持流式数据的多种处理操作
License: MIT
Keywords: ant-chain,antchain,data-processing,stream-processing,data-chain
Author: tumingjian
Author-email: tumingjian@qq.com
Requires-Python: >=3.10
Classifier: Development Status :: 3 - Alpha
Classifier: Intended Audience :: Developers
Classifier: License :: OSI Approved :: MIT License
Classifier: Programming Language :: Python :: 3
Classifier: Programming Language :: Python :: 3.10
Classifier: Programming Language :: Python :: 3.11
Classifier: Programming Language :: Python :: 3.12
Classifier: Topic :: Software Development :: Libraries :: Python Modules
Classifier: Topic :: Utilities
Project-URL: Bug Tracker, https://github.com/chinese-code/antchain/issues
Project-URL: Homepage, https://github.com/chinese-code/antchain
Project-URL: Repository, https://github.com/chinese-code/antchain.git
